teleboting/__init__.py
teleboting/auth.py
teleboting/main.py
teleboting/api/__init__.py
teleboting/api/connector.py
teleboting/validators/__init__.py
teleboting/validators/exceptions.py
teleboting/validators/input.py
teleboting-0.0.10.dist-info/METADATA
teleboting-0.0.10.dist-info/WHEEL
teleboting-0.0.10.dist-info/RECORD
