Metadata-Version: 2.4
Name: teleboting
Version: 0.0.10
Author-email: Тихонович Артем Олегович <braynt.k@mail.ru>
Classifier: License :: OSI Approved :: MIT License
Classifier: Operating System :: OS Independent
Classifier: Programming Language :: Python :: 3
Requires-Python: >=3.11.0
Requires-Dist: pytelegrambotapi>=4.26.0
